PyPap3r/__init__.py
PyPap3r/main.py
PyPap3r-1.0.6.dist-info/LICENSE
PyPap3r-1.0.6.dist-info/METADATA
PyPap3r-1.0.6.dist-info/WHEEL
PyPap3r-1.0.6.dist-info/top_level.txt
PyPap3r-1.0.6.dist-info/RECORD
