Metadata-Version: 2.1
Name: PyPap3r
Version: 1.0.6
Summary: A python package that can change your mac's wallpaper to a file or a url. It can also download images.
Home-page: https://github.com/TheBaconPug/PyPap3r
Author: TheBaconPug
License: UNKNOWN
Platform: UNKNOWN
Classifier: Programming Language :: Python :: 3
Classifier: License :: OSI Approved :: MIT License
Classifier: Operating System :: MacOS
Requires-Python: >=3.8
